{"_invocation_id": "6409a7ff-5702-4dd5-95db-9a53d6329f00", "linked": {"0": {"name": "source.PROJECT_CICD_DEMO.tpch.orders", "type": "source", "succ": [20, 60, 61, 62, 65]}, "1": {"name": "source.PROJECT_CICD_DEMO.tpch.customer", "type": "source", "succ": [23, 62, 63, 64]}, "2": {"name": "source.PROJECT_CICD_DEMO.tpch.lineitem", "type": "source", "succ": [24, 65, 66, 67]}, "3": {"name": "source.PROJECT_CICD_DEMO.tpch.nation", "type": "source", "succ": [15, 68, 69, 70, 79]}, "4": {"name": "source.PROJECT_CICD_DEMO.tpch.part", "type": "source", "succ": [12, 66, 71, 72, 73]}, "5": {"name": "source.PROJECT_CICD_DEMO.tpch.partsupp", "type": "source", "succ": [25, 73, 74]}, "6": {"name": "source.PROJECT_CICD_DEMO.tpch.region", "type": "source", "succ": [16, 70, 75, 76]}, "7": {"name": "source.PROJECT_CICD_DEMO.tpch.supplier", "type": "source", "succ": [14, 67, 74, 77, 78, 79]}, "8": {"name": "model.PROJECT_CICD_DEMO.agg_ship_modes_dynamic_pivot", "type": "model", "succ": [80]}, "9": {"name": "model.PROJECT_CICD_DEMO.fct_order_items", "type": "model", "succ": [8, 10, 35, 36]}, "10": {"name": "model.PROJECT_CICD_DEMO.agg_ship_modes_hardcoded_pivot", "type": "model"}, "11": {"name": "model.PROJECT_CICD_DEMO.dim_parts", "type": "model", "succ": [31, 32]}, "12": {"name": "model.PROJECT_CICD_DEMO.stg_tpch_parts", "type": "model", "succ": [11, 18, 54, 55]}, "13": {"name": "model.PROJECT_CICD_DEMO.dim_suppliers", "type": "model", "succ": [33, 34]}, "14": {"name": "model.PROJECT_CICD_DEMO.stg_tpch_suppliers", "type": "model", "succ": [13, 18, 58, 59]}, "15": {"name": "model.PROJECT_CICD_DEMO.stg_tpch_nations", "type": "model", "succ": [13, 22, 48, 49]}, "16": {"name": "model.PROJECT_CICD_DEMO.stg_tpch_regions", "type": "model", "succ": [13, 22, 56, 57]}, "17": {"name": "model.PROJECT_CICD_DEMO.order_items", "type": "model", "succ": [9, 19, 21, 40, 41]}, "18": {"name": "model.PROJECT_CICD_DEMO.part_suppliers", "type": "model", "succ": [9, 42, 43]}, "19": {"name": "model.PROJECT_CICD_DEMO.fct_orders", "type": "model", "succ": [37, 38, 39]}, "20": {"name": "model.PROJECT_CICD_DEMO.stg_tpch_orders", "type": "model", "succ": [19, 21, 17, 50, 51]}, "21": {"name": "model.PROJECT_CICD_DEMO.incremental_dim_orders", "type": "model", "succ": [26]}, "22": {"name": "model.PROJECT_CICD_DEMO.dim_customers", "type": "model", "succ": [28, 29, 30, 39]}, "23": {"name": "model.PROJECT_CICD_DEMO.stg_tpch_customers", "type": "model", "succ": [22, 44, 45]}, "24": {"name": "model.PROJECT_CICD_DEMO.stg_tpch_line_items", "type": "model", "succ": [17, 46, 47]}, "25": {"name": "model.PROJECT_CICD_DEMO.stg_tpch_part_suppliers", "type": "model", "succ": [18, 52, 53]}, "26": {"name": "analysis.PROJECT_CICD_DEMO.show_incremental_model", "type": "analysis"}, "27": {"name": "operation.PROJECT_CICD_DEMO.PROJECT_CICD_DEMO-on-run-end-0", "type": "operation"}, "28": {"name": "test.PROJECT_CICD_DEMO.unique_dim_customers_customer_key.ad8156656e", "type": "test"}, "29": {"name": "test.PROJECT_CICD_DEMO.not_null_dim_customers_customer_key.4bebfb3411", "type": "test"}, "30": {"name": "test.PROJECT_CICD_DEMO.accepted_values_dim_customers_region__AFRICA__MIDDLE_EAST__ASIA__EUROPE__AMERICA.dad4601b69", "type": "test"}, "31": {"name": "test.PROJECT_CICD_DEMO.unique_dim_parts_part_key.712df18d58", "type": "test"}, "32": {"name": "test.PROJECT_CICD_DEMO.not_null_dim_parts_part_key.4358f880d9", "type": "test"}, "33": {"name": "test.PROJECT_CICD_DEMO.unique_dim_suppliers_supplier_key.58fc3e4770", "type": "test"}, "34": {"name": "test.PROJECT_CICD_DEMO.not_null_dim_suppliers_supplier_key.4315350956", "type": "test"}, "35": {"name": "test.PROJECT_CICD_DEMO.unique_fct_order_items_order_item_key.4d6426a255", "type": "test"}, "36": {"name": "test.PROJECT_CICD_DEMO.not_null_fct_order_items_order_item_key.47516a6371", "type": "test"}, "37": {"name": "test.PROJECT_CICD_DEMO.unique_fct_orders_order_key.f5e7a90273", "type": "test"}, "38": {"name": "test.PROJECT_CICD_DEMO.not_null_fct_orders_order_key.6a6f83ab15", "type": "test"}, "39": {"name": "test.PROJECT_CICD_DEMO.relationships_fct_orders_customer_key__customer_key__ref_dim_customers_.018eb0a60b", "type": "test"}, "40": {"name": "test.PROJECT_CICD_DEMO.unique_order_items_order_item_key.43a40b2837", "type": "test"}, "41": {"name": "test.PROJECT_CICD_DEMO.not_null_order_items_order_item_key.44b9fa7311", "type": "test"}, "42": {"name": "test.PROJECT_CICD_DEMO.unique_part_suppliers_part_supplier_key.909477afa8", "type": "test"}, "43": {"name": "test.PROJECT_CICD_DEMO.not_null_part_suppliers_part_supplier_key.b8b2022ed3", "type": "test"}, "44": {"name": "test.PROJECT_CICD_DEMO.unique_stg_tpch_customers_customer_key.7f1a18b1a4", "type": "test"}, "45": {"name": "test.PROJECT_CICD_DEMO.not_null_stg_tpch_customers_customer_key.a10e15535a", "type": "test"}, "46": {"name": "test.PROJECT_CICD_DEMO.unique_stg_tpch_line_items_order_item_key.c819d91e0a", "type": "test"}, "47": {"name": "test.PROJECT_CICD_DEMO.not_null_stg_tpch_line_items_order_item_key.cd47c7a679", "type": "test"}, "48": {"name": "test.PROJECT_CICD_DEMO.unique_stg_tpch_nations_nation_key.9e3675553d", "type": "test"}, "49": {"name": "test.PROJECT_CICD_DEMO.not_null_stg_tpch_nations_nation_key.d0c2fe32ed", "type": "test"}, "50": {"name": "test.PROJECT_CICD_DEMO.unique_stg_tpch_orders_order_key.bd29f13cc9", "type": "test"}, "51": {"name": "test.PROJECT_CICD_DEMO.not_null_stg_tpch_orders_order_key.bb22e75ae8", "type": "test"}, "52": {"name": "test.PROJECT_CICD_DEMO.unique_stg_tpch_part_suppliers_part_supplier_key.96ab01c1ae", "type": "test"}, "53": {"name": "test.PROJECT_CICD_DEMO.not_null_stg_tpch_part_suppliers_part_supplier_key.3cc6ccee2e", "type": "test"}, "54": {"name": "test.PROJECT_CICD_DEMO.unique_stg_tpch_parts_part_key.afbc7ad489", "type": "test"}, "55": {"name": "test.PROJECT_CICD_DEMO.not_null_stg_tpch_parts_part_key.cc8e610420", "type": "test"}, "56": {"name": "test.PROJECT_CICD_DEMO.unique_stg_tpch_regions_region_key.b2bd891bb5", "type": "test"}, "57": {"name": "test.PROJECT_CICD_DEMO.not_null_stg_tpch_regions_region_key.869fa0b326", "type": "test"}, "58": {"name": "test.PROJECT_CICD_DEMO.unique_stg_tpch_suppliers_supplier_key.6215308464", "type": "test"}, "59": {"name": "test.PROJECT_CICD_DEMO.not_null_stg_tpch_suppliers_supplier_key.97c31a786d", "type": "test"}, "60": {"name": "test.PROJECT_CICD_DEMO.source_unique_tpch_orders_o_orderkey.374f048af2", "type": "test"}, "61": {"name": "test.PROJECT_CICD_DEMO.source_not_null_tpch_orders_o_orderkey.ebd571817b", "type": "test"}, "62": {"name": "test.PROJECT_CICD_DEMO.source_relationships_tpch_orders_o_custkey__c_custkey__source_tpch_customer_.024e40ec67", "type": "test"}, "63": {"name": "test.PROJECT_CICD_DEMO.source_unique_tpch_customer_c_custkey.048e97fc25", "type": "test"}, "64": {"name": "test.PROJECT_CICD_DEMO.source_not_null_tpch_customer_c_custkey.a95b6298b5", "type": "test"}, "65": {"name": "test.PROJECT_CICD_DEMO.source_relationships_tpch_lineitem_l_orderkey__o_orderkey__source_tpch_orders_.f722cb898d", "type": "test"}, "66": {"name": "test.PROJECT_CICD_DEMO.source_relationships_tpch_lineitem_l_partkey__p_partkey__source_tpch_part_.b761c77df8", "type": "test"}, "67": {"name": "test.PROJECT_CICD_DEMO.source_relationships_tpch_lineitem_l_suppkey__s_suppkey__source_tpch_supplier_.f872fb81a2", "type": "test"}, "68": {"name": "test.PROJECT_CICD_DEMO.source_unique_tpch_nation_n_nationkey.3bd4153064", "type": "test"}, "69": {"name": "test.PROJECT_CICD_DEMO.source_not_null_tpch_nation_n_nationkey.5ac5d27298", "type": "test"}, "70": {"name": "test.PROJECT_CICD_DEMO.source_relationships_tpch_nation_n_regionkey__r_regionkey__source_tpch_region_.116e1ee3da", "type": "test"}, "71": {"name": "test.PROJECT_CICD_DEMO.source_unique_tpch_part_p_partkey.30b171988e", "type": "test"}, "72": {"name": "test.PROJECT_CICD_DEMO.source_not_null_tpch_part_p_partkey.9543847190", "type": "test"}, "73": {"name": "test.PROJECT_CICD_DEMO.source_relationships_tpch_partsupp_ps_partkey__p_partkey__source_tpch_part_.511196222f", "type": "test"}, "74": {"name": "test.PROJECT_CICD_DEMO.source_relationships_tpch_partsupp_ps_suppkey__s_suppkey__source_tpch_supplier_.1c7ef0743e", "type": "test"}, "75": {"name": "test.PROJECT_CICD_DEMO.source_unique_tpch_region_r_regionkey.d8eeced103", "type": "test"}, "76": {"name": "test.PROJECT_CICD_DEMO.source_not_null_tpch_region_r_regionkey.8f6ee68076", "type": "test"}, "77": {"name": "test.PROJECT_CICD_DEMO.source_unique_tpch_supplier_s_suppkey.1a36cf4370", "type": "test"}, "78": {"name": "test.PROJECT_CICD_DEMO.source_not_null_tpch_supplier_s_suppkey.94660e6dab", "type": "test"}, "79": {"name": "test.PROJECT_CICD_DEMO.source_relationships_tpch_supplier_s_nationkey__n_nationkey__source_tpch_nation_.2a47ee53da", "type": "test"}, "80": {"name": "exposure.PROJECT_CICD_DEMO.yearly_part_rollup", "type": "exposure"}}, "with_test_edges": {"0": {"name": "source.PROJECT_CICD_DEMO.tpch.orders", "type": "source", "succ": [20, 60, 61, 62, 65]}, "1": {"name": "source.PROJECT_CICD_DEMO.tpch.customer", "type": "source", "succ": [23, 62, 63, 64]}, "2": {"name": "source.PROJECT_CICD_DEMO.tpch.lineitem", "type": "source", "succ": [24, 65, 66, 67]}, "3": {"name": "source.PROJECT_CICD_DEMO.tpch.nation", "type": "source", "succ": [15, 68, 69, 70, 79]}, "4": {"name": "source.PROJECT_CICD_DEMO.tpch.part", "type": "source", "succ": [12, 66, 71, 72, 73]}, "5": {"name": "source.PROJECT_CICD_DEMO.tpch.partsupp", "type": "source", "succ": [25, 73, 74]}, "6": {"name": "source.PROJECT_CICD_DEMO.tpch.region", "type": "source", "succ": [16, 70, 75, 76]}, "7": {"name": "source.PROJECT_CICD_DEMO.tpch.supplier", "type": "source", "succ": [14, 67, 74, 77, 78, 79]}, "8": {"name": "model.PROJECT_CICD_DEMO.agg_ship_modes_dynamic_pivot", "type": "model", "succ": [80]}, "9": {"name": "model.PROJECT_CICD_DEMO.fct_order_items", "type": "model", "succ": [8, 10, 35, 36]}, "10": {"name": "model.PROJECT_CICD_DEMO.agg_ship_modes_hardcoded_pivot", "type": "model"}, "11": {"name": "model.PROJECT_CICD_DEMO.dim_parts", "type": "model", "succ": [31, 32]}, "12": {"name": "model.PROJECT_CICD_DEMO.stg_tpch_parts", "type": "model", "succ": [11, 18, 54, 55]}, "13": {"name": "model.PROJECT_CICD_DEMO.dim_suppliers", "type": "model", "succ": [33, 34]}, "14": {"name": "model.PROJECT_CICD_DEMO.stg_tpch_suppliers", "type": "model", "succ": [13, 18, 58, 59]}, "15": {"name": "model.PROJECT_CICD_DEMO.stg_tpch_nations", "type": "model", "succ": [13, 22, 48, 49]}, "16": {"name": "model.PROJECT_CICD_DEMO.stg_tpch_regions", "type": "model", "succ": [13, 22, 56, 57]}, "17": {"name": "model.PROJECT_CICD_DEMO.order_items", "type": "model", "succ": [9, 19, 21, 40, 41]}, "18": {"name": "model.PROJECT_CICD_DEMO.part_suppliers", "type": "model", "succ": [9, 42, 43]}, "19": {"name": "model.PROJECT_CICD_DEMO.fct_orders", "type": "model", "succ": [37, 38, 39]}, "20": {"name": "model.PROJECT_CICD_DEMO.stg_tpch_orders", "type": "model", "succ": [19, 21, 17, 50, 51]}, "21": {"name": "model.PROJECT_CICD_DEMO.incremental_dim_orders", "type": "model", "succ": [26]}, "22": {"name": "model.PROJECT_CICD_DEMO.dim_customers", "type": "model", "succ": [28, 29, 30, 39]}, "23": {"name": "model.PROJECT_CICD_DEMO.stg_tpch_customers", "type": "model", "succ": [22, 44, 45]}, "24": {"name": "model.PROJECT_CICD_DEMO.stg_tpch_line_items", "type": "model", "succ": [17, 46, 47]}, "25": {"name": "model.PROJECT_CICD_DEMO.stg_tpch_part_suppliers", "type": "model", "succ": [18, 52, 53]}, "26": {"name": "analysis.PROJECT_CICD_DEMO.show_incremental_model", "type": "analysis"}, "27": {"name": "operation.PROJECT_CICD_DEMO.PROJECT_CICD_DEMO-on-run-end-0", "type": "operation"}, "28": {"name": "test.PROJECT_CICD_DEMO.unique_dim_customers_customer_key.ad8156656e", "type": "test"}, "29": {"name": "test.PROJECT_CICD_DEMO.not_null_dim_customers_customer_key.4bebfb3411", "type": "test"}, "30": {"name": "test.PROJECT_CICD_DEMO.accepted_values_dim_customers_region__AFRICA__MIDDLE_EAST__ASIA__EUROPE__AMERICA.dad4601b69", "type": "test"}, "31": {"name": "test.PROJECT_CICD_DEMO.unique_dim_parts_part_key.712df18d58", "type": "test"}, "32": {"name": "test.PROJECT_CICD_DEMO.not_null_dim_parts_part_key.4358f880d9", "type": "test"}, "33": {"name": "test.PROJECT_CICD_DEMO.unique_dim_suppliers_supplier_key.58fc3e4770", "type": "test"}, "34": {"name": "test.PROJECT_CICD_DEMO.not_null_dim_suppliers_supplier_key.4315350956", "type": "test"}, "35": {"name": "test.PROJECT_CICD_DEMO.unique_fct_order_items_order_item_key.4d6426a255", "type": "test", "succ": [8, 10]}, "36": {"name": "test.PROJECT_CICD_DEMO.not_null_fct_order_items_order_item_key.47516a6371", "type": "test", "succ": [8, 10]}, "37": {"name": "test.PROJECT_CICD_DEMO.unique_fct_orders_order_key.f5e7a90273", "type": "test"}, "38": {"name": "test.PROJECT_CICD_DEMO.not_null_fct_orders_order_key.6a6f83ab15", "type": "test"}, "39": {"name": "test.PROJECT_CICD_DEMO.relationships_fct_orders_customer_key__customer_key__ref_dim_customers_.018eb0a60b", "type": "test"}, "40": {"name": "test.PROJECT_CICD_DEMO.unique_order_items_order_item_key.43a40b2837", "type": "test", "succ": [8, 9, 10, 19, 21, 26]}, "41": {"name": "test.PROJECT_CICD_DEMO.not_null_order_items_order_item_key.44b9fa7311", "type": "test", "succ": [8, 9, 10, 19, 21, 26]}, "42": {"name": "test.PROJECT_CICD_DEMO.unique_part_suppliers_part_supplier_key.909477afa8", "type": "test", "succ": [8, 9, 10]}, "43": {"name": "test.PROJECT_CICD_DEMO.not_null_part_suppliers_part_supplier_key.b8b2022ed3", "type": "test", "succ": [8, 9, 10]}, "44": {"name": "test.PROJECT_CICD_DEMO.unique_stg_tpch_customers_customer_key.7f1a18b1a4", "type": "test", "succ": [22]}, "45": {"name": "test.PROJECT_CICD_DEMO.not_null_stg_tpch_customers_customer_key.a10e15535a", "type": "test", "succ": [22]}, "46": {"name": "test.PROJECT_CICD_DEMO.unique_stg_tpch_line_items_order_item_key.c819d91e0a", "type": "test", "succ": [8, 9, 10, 17, 19, 21, 26]}, "47": {"name": "test.PROJECT_CICD_DEMO.not_null_stg_tpch_line_items_order_item_key.cd47c7a679", "type": "test", "succ": [8, 9, 10, 17, 19, 21, 26]}, "48": {"name": "test.PROJECT_CICD_DEMO.unique_stg_tpch_nations_nation_key.9e3675553d", "type": "test", "succ": [13, 22]}, "49": {"name": "test.PROJECT_CICD_DEMO.not_null_stg_tpch_nations_nation_key.d0c2fe32ed", "type": "test", "succ": [13, 22]}, "50": {"name": "test.PROJECT_CICD_DEMO.unique_stg_tpch_orders_order_key.bd29f13cc9", "type": "test", "succ": [8, 9, 10, 17, 19, 21, 26]}, "51": {"name": "test.PROJECT_CICD_DEMO.not_null_stg_tpch_orders_order_key.bb22e75ae8", "type": "test", "succ": [8, 9, 10, 17, 19, 21, 26]}, "52": {"name": "test.PROJECT_CICD_DEMO.unique_stg_tpch_part_suppliers_part_supplier_key.96ab01c1ae", "type": "test", "succ": [8, 9, 10, 18]}, "53": {"name": "test.PROJECT_CICD_DEMO.not_null_stg_tpch_part_suppliers_part_supplier_key.3cc6ccee2e", "type": "test", "succ": [8, 9, 10, 18]}, "54": {"name": "test.PROJECT_CICD_DEMO.unique_stg_tpch_parts_part_key.afbc7ad489", "type": "test", "succ": [8, 9, 10, 11, 18]}, "55": {"name": "test.PROJECT_CICD_DEMO.not_null_stg_tpch_parts_part_key.cc8e610420", "type": "test", "succ": [8, 9, 10, 11, 18]}, "56": {"name": "test.PROJECT_CICD_DEMO.unique_stg_tpch_regions_region_key.b2bd891bb5", "type": "test", "succ": [13, 22]}, "57": {"name": "test.PROJECT_CICD_DEMO.not_null_stg_tpch_regions_region_key.869fa0b326", "type": "test", "succ": [13, 22]}, "58": {"name": "test.PROJECT_CICD_DEMO.unique_stg_tpch_suppliers_supplier_key.6215308464", "type": "test", "succ": [8, 9, 10, 13, 18]}, "59": {"name": "test.PROJECT_CICD_DEMO.not_null_stg_tpch_suppliers_supplier_key.97c31a786d", "type": "test", "succ": [8, 9, 10, 13, 18]}, "60": {"name": "test.PROJECT_CICD_DEMO.source_unique_tpch_orders_o_orderkey.374f048af2", "type": "test", "succ": [8, 9, 10, 17, 19, 20, 21, 26]}, "61": {"name": "test.PROJECT_CICD_DEMO.source_not_null_tpch_orders_o_orderkey.ebd571817b", "type": "test", "succ": [8, 9, 10, 17, 19, 20, 21, 26]}, "62": {"name": "test.PROJECT_CICD_DEMO.source_relationships_tpch_orders_o_custkey__c_custkey__source_tpch_customer_.024e40ec67", "type": "test"}, "63": {"name": "test.PROJECT_CICD_DEMO.source_unique_tpch_customer_c_custkey.048e97fc25", "type": "test", "succ": [22, 23]}, "64": {"name": "test.PROJECT_CICD_DEMO.source_not_null_tpch_customer_c_custkey.a95b6298b5", "type": "test", "succ": [22, 23]}, "65": {"name": "test.PROJECT_CICD_DEMO.source_relationships_tpch_lineitem_l_orderkey__o_orderkey__source_tpch_orders_.f722cb898d", "type": "test", "succ": [8, 9, 10, 17, 19, 21, 26]}, "66": {"name": "test.PROJECT_CICD_DEMO.source_relationships_tpch_lineitem_l_partkey__p_partkey__source_tpch_part_.b761c77df8", "type": "test", "succ": [8, 9, 10]}, "67": {"name": "test.PROJECT_CICD_DEMO.source_relationships_tpch_lineitem_l_suppkey__s_suppkey__source_tpch_supplier_.f872fb81a2", "type": "test", "succ": [8, 9, 10]}, "68": {"name": "test.PROJECT_CICD_DEMO.source_unique_tpch_nation_n_nationkey.3bd4153064", "type": "test", "succ": [13, 15, 22]}, "69": {"name": "test.PROJECT_CICD_DEMO.source_not_null_tpch_nation_n_nationkey.5ac5d27298", "type": "test", "succ": [13, 15, 22]}, "70": {"name": "test.PROJECT_CICD_DEMO.source_relationships_tpch_nation_n_regionkey__r_regionkey__source_tpch_region_.116e1ee3da", "type": "test", "succ": [13, 22]}, "71": {"name": "test.PROJECT_CICD_DEMO.source_unique_tpch_part_p_partkey.30b171988e", "type": "test", "succ": [8, 9, 10, 11, 12, 18]}, "72": {"name": "test.PROJECT_CICD_DEMO.source_not_null_tpch_part_p_partkey.9543847190", "type": "test", "succ": [8, 9, 10, 11, 12, 18]}, "73": {"name": "test.PROJECT_CICD_DEMO.source_relationships_tpch_partsupp_ps_partkey__p_partkey__source_tpch_part_.511196222f", "type": "test", "succ": [8, 9, 10, 18]}, "74": {"name": "test.PROJECT_CICD_DEMO.source_relationships_tpch_partsupp_ps_suppkey__s_suppkey__source_tpch_supplier_.1c7ef0743e", "type": "test", "succ": [8, 9, 10, 18]}, "75": {"name": "test.PROJECT_CICD_DEMO.source_unique_tpch_region_r_regionkey.d8eeced103", "type": "test", "succ": [13, 16, 22]}, "76": {"name": "test.PROJECT_CICD_DEMO.source_not_null_tpch_region_r_regionkey.8f6ee68076", "type": "test", "succ": [13, 16, 22]}, "77": {"name": "test.PROJECT_CICD_DEMO.source_unique_tpch_supplier_s_suppkey.1a36cf4370", "type": "test", "succ": [8, 9, 10, 13, 14, 18]}, "78": {"name": "test.PROJECT_CICD_DEMO.source_not_null_tpch_supplier_s_suppkey.94660e6dab", "type": "test", "succ": [8, 9, 10, 13, 14, 18]}, "79": {"name": "test.PROJECT_CICD_DEMO.source_relationships_tpch_supplier_s_nationkey__n_nationkey__source_tpch_nation_.2a47ee53da", "type": "test", "succ": [13]}, "80": {"name": "exposure.PROJECT_CICD_DEMO.yearly_part_rollup", "type": "exposure"}}}